thepysec/__init__.py
thepysec/lia.py
thepysec/matina.py
thepysec/myriam.py
thepysec/otto.py
thepysec/thanos.py
thepysec/john/__init__.py
thepysec/john/version.py
thepysec/john/tests/__init__.py
thepysec/john/tests/test_version.py
thepysec-2.2.1.dist-info/LICENSE
thepysec-2.2.1.dist-info/METADATA
thepysec-2.2.1.dist-info/WHEEL
thepysec-2.2.1.dist-info/top_level.txt
thepysec-2.2.1.dist-info/RECORD
