Metadata-Version: 2.1
Name: thepysec
Version: 2.2.1
Summary: Python secretaries you call at will, for instant py-relief.
Home-page: https://github.com/raratiru/thepysec
Author: Raratiru
Author-email: info@musicaloffering.gr
License: BSD 3-Clause License
Classifier: Development Status :: 1 - Planning
Classifier: Programming Language :: Python :: 3
Classifier: Programming Language :: Python :: 3.8
Classifier: Programming Language :: Python :: 3.9
Classifier: Programming Language :: Python :: 3.10
Classifier: Programming Language :: Python :: 3.11
Classifier: License :: OSI Approved :: BSD License
Classifier: Operating System :: OS Independent
Classifier: Natural Language :: English
Classifier: Topic :: Software Development :: Libraries :: Python Modules
Requires-Python: >=3.8
License-File: LICENSE
Requires-Dist: unidecode
Provides-Extra: dev
Requires-Dist: pytest ; extra == 'dev'
Requires-Dist: pytest-cov ; extra == 'dev'
Requires-Dist: ipdb ; extra == 'dev'
Requires-Dist: psycopg2-binary ; extra == 'dev'
